medscan/__init__.py
medscan/config.py
medscan/data.py
medscan/pipeline.py
medscan/predict.py
medscan/train.py
medscan/transform.py
medscan-0.1.5.dist-info/METADATA
medscan-0.1.5.dist-info/WHEEL
medscan-0.1.5.dist-info/top_level.txt
medscan-0.1.5.dist-info/RECORD
